peaktrackingtotemp/__init__.py
peaktrackingtotemp/_version.py
peaktrackingtotemp/core.py
peaktrackingtotemp/tests/__init__.py
peaktrackingtotemp/tests/conftest.py
peaktrackingtotemp/tests/test_examples.py
peaktrackingtotemp-0.0.0.dist-info/AUTHORS.rst
peaktrackingtotemp-0.0.0.dist-info/LICENSE
peaktrackingtotemp-0.0.0.dist-info/METADATA
peaktrackingtotemp-0.0.0.dist-info/WHEEL
peaktrackingtotemp-0.0.0.dist-info/top_level.txt
peaktrackingtotemp-0.0.0.dist-info/RECORD
