Metadata-Version: 2.1
Name: peaktrackingtotemp
Version: 0.0.0
Summary: Simple tool to track temperature changes in a stream of XRD data.
Home-page: https://github.com/jonathanjdenney/peaktrackingtotemp
Author: Jonathan Denney
Author-email: jonathan.denney@stonybrook.edu
License: BSD (3-clause)
Platform: UNKNOWN
Classifier: Development Status :: 2 - Pre-Alpha
Classifier: Natural Language :: English
Classifier: Programming Language :: Python :: 3
Requires-Python: >=3.9
License-File: LICENSE
License-File: AUTHORS.rst
